odoo/addons/pos_to_weight_by_product_uom/README.rst
odoo/addons/pos_to_weight_by_product_uom/__init__.py
odoo/addons/pos_to_weight_by_product_uom/__manifest__.py
odoo/addons/pos_to_weight_by_product_uom/hooks.py
odoo/addons/pos_to_weight_by_product_uom/i18n/ca.po
odoo/addons/pos_to_weight_by_product_uom/i18n/de.po
odoo/addons/pos_to_weight_by_product_uom/i18n/es.po
odoo/addons/pos_to_weight_by_product_uom/i18n/es_MX.po
odoo/addons/pos_to_weight_by_product_uom/i18n/fi.po
odoo/addons/pos_to_weight_by_product_uom/i18n/fr.po
odoo/addons/pos_to_weight_by_product_uom/i18n/fr_CH.po
odoo/addons/pos_to_weight_by_product_uom/i18n/hr.po
odoo/addons/pos_to_weight_by_product_uom/i18n/hr_HR.po
odoo/addons/pos_to_weight_by_product_uom/i18n/it.po
odoo/addons/pos_to_weight_by_product_uom/i18n/pos_to_weight_by_product_uom.pot
odoo/addons/pos_to_weight_by_product_uom/i18n/pt.po
odoo/addons/pos_to_weight_by_product_uom/i18n/pt_BR.po
odoo/addons/pos_to_weight_by_product_uom/i18n/ro.po
odoo/addons/pos_to_weight_by_product_uom/i18n/sl.po
odoo/addons/pos_to_weight_by_product_uom/i18n/tr_TR.po
odoo/addons/pos_to_weight_by_product_uom/i18n/vi_VN.po
odoo/addons/pos_to_weight_by_product_uom/i18n/zh_CN.po
odoo/addons/pos_to_weight_by_product_uom/migrations/16.0.1.0.0/pre-migration.py
odoo/addons/pos_to_weight_by_product_uom/models/__init__.py
odoo/addons/pos_to_weight_by_product_uom/models/product_product.py
odoo/addons/pos_to_weight_by_product_uom/models/product_template.py
odoo/addons/pos_to_weight_by_product_uom/models/uom_category.py
odoo/addons/pos_to_weight_by_product_uom/models/uom_uom.py
odoo/addons/pos_to_weight_by_product_uom/readme/CONFIGURE.rst
odoo/addons/pos_to_weight_by_product_uom/readme/CONTRIBUTORS.rst
odoo/addons/pos_to_weight_by_product_uom/readme/DESCRIPTION.rst
odoo/addons/pos_to_weight_by_product_uom/readme/USAGE.rst
odoo/addons/pos_to_weight_by_product_uom/static/description/icon.png
odoo/addons/pos_to_weight_by_product_uom/static/description/index.html
odoo_addon_pos_to_weight_by_product_uom-16.0.1.0.0.6.dist-info/METADATA
odoo_addon_pos_to_weight_by_product_uom-16.0.1.0.0.6.dist-info/WHEEL
odoo_addon_pos_to_weight_by_product_uom-16.0.1.0.0.6.dist-info/top_level.txt
odoo_addon_pos_to_weight_by_product_uom-16.0.1.0.0.6.dist-info/RECORD
